jupyterlab_powerpoint/__init__.py
jupyterlab_powerpoint/_version.py
jupyterlab_powerpoint/extension.py
jupyterlab_powerpoint/presentation.py
jupyterlab_powerpoint/tests/__init__.py
jupyterlab_powerpoint/tests/test_all.py
jupyterlab_powerpoint/tests/test_extension.py
jupyterlab_powerpoint/tests/test_init.py
jupyterlab_powerpoint/tests/test_presentation.py
jupyterlab_powerpoint/tests/js/activate.test.ts
jupyterlab_powerpoint/tests/js/assetsTransformer.js
jupyterlab_powerpoint/tests/js/export.test.ts
jupyterlab_powerpoint/tests/js/fileMock.js
jupyterlab_powerpoint/tests/js/styleMock.js
jupyterlab_powerpoint-0.1.0.data/data/etc/jupyter/jupyter_notebook_config.d/jupyterlab_powerpoint.json
jupyterlab_powerpoint-0.1.0.data/data/share/jupyter/lab/extensions/jupyterlab_powerpoint-0.1.0.tgz
jupyterlab_powerpoint-0.1.0.dist-info/LICENSE
jupyterlab_powerpoint-0.1.0.dist-info/METADATA
jupyterlab_powerpoint-0.1.0.dist-info/WHEEL
jupyterlab_powerpoint-0.1.0.dist-info/top_level.txt
jupyterlab_powerpoint-0.1.0.dist-info/RECORD
