Metadata-Version: 2.1
Name: jupyterlab-powerpoint
Version: 0.1.0
Summary: Create powerpoints from jupyter notebooks
Home-page: https://github.com/timkpaine/jupyterlab_powerpoint
Author: Tim Paine
Author-email: t.paine154@gmail.com
License: Apache 2.0
Keywords: jupyter jupyterlab
Platform: UNKNOWN
Classifier: Development Status :: 3 - Alpha
Classifier: Programming Language :: Python :: 2
Classifier: Programming Language :: Python :: 2.7
Classifier: Programming Language :: Python :: 3
Classifier: Programming Language :: Python :: 3.6
Classifier: Programming Language :: Python :: 3.7
Classifier: Programming Language :: Python :: 3.8
Classifier: Framework :: Jupyter
Requires-Dist: jupyterlab (>=1.0.0)
Requires-Dist: nbconvert (>=5.5.0)
Requires-Dist: nbformat (>=4.4.0)
Requires-Dist: python-pptx (>=0.6.0)
Provides-Extra: dev
Requires-Dist: jupyterlab (>=1.0.0) ; extra == 'dev'
Requires-Dist: nbconvert (>=5.5.0) ; extra == 'dev'
Requires-Dist: nbformat (>=4.4.0) ; extra == 'dev'
Requires-Dist: python-pptx (>=0.6.0) ; extra == 'dev'
Requires-Dist: pytest ; extra == 'dev'
Requires-Dist: pytest-cov ; extra == 'dev'
Requires-Dist: pylint ; extra == 'dev'
Requires-Dist: flake8 ; extra == 'dev'
Requires-Dist: bump2version ; extra == 'dev'
Requires-Dist: autopep8 ; extra == 'dev'
Requires-Dist: mock ; extra == 'dev'
